LICENSE
MANIFEST.in
README.rst
setup.py
osxmmkeys/__init__.py
osxmmkeys/tap.py
osxmmkeys.egg-info/PKG-INFO
osxmmkeys.egg-info/SOURCES.txt
osxmmkeys.egg-info/dependency_links.txt
osxmmkeys.egg-info/requires.txt
osxmmkeys.egg-info/top_level.txt